LICENSE
README.md
setup.py
vmware_wrapper/__init__.py
vmware_wrapper/config.py
vmware_wrapper/vmware_wrapper.py
vmware_wrapper.egg-info/PKG-INFO
vmware_wrapper.egg-info/SOURCES.txt
vmware_wrapper.egg-info/dependency_links.txt
vmware_wrapper.egg-info/requires.txt
vmware_wrapper.egg-info/top_level.txt